<annotation><folder>11--Meeting</folder><filename>11_Meeting_Meeting_11_Meeting_Meeting_11_923.jpg</filename><path>./WIDER_train/images/11--Meeting/11_Meeting_Meeting_11_Meeting_Meeting_11_923.jpg</path><source><database>Unknown</database></source><size><width>1024</width><height>768</height><depth>3</depth></size><segmented>0</segmented><object><name>face</name><pose>Unspecified</pose><truncated>0</truncated><difficult>0</difficult><bndbox><xmin>252</xmin><ymin>386</ymin><xmax>332</xmax><ymax>496</ymax></bndbox></object><object><name>face</name><pose>Unspecified</pose><truncated>0</truncated><difficult>0</difficult><bndbox><xmin>706</xmin><ymin>570</ymin><xmax>814</xmax><ymax>704</ymax></bndbox></object><object><name>face</name><pose>Unspecified</pose><truncated>0</truncated><difficult>0</difficult><bndbox><xmin>718</xmin><ymin>402</ymin><xmax>798</xmax><ymax>506</ymax></bndbox></object><object><name>face</name><pose>Unspecified</pose><truncated>0</truncated><difficult>0</difficult><bndbox><xmin>754</xmin><ymin>242</ymin><xmax>814</xmax><ymax>316</ymax></bndbox></object><object><name>face</name><pose>Unspecified</pose><truncated>0</truncated><difficult>0</difficult><bndbox><xmin>928</xmin><ymin>194</ymin><xmax>984</xmax><ymax>252</ymax></bndbox></object><object><name>face</name><pose>Unspecified</pose><truncated>0</truncated><difficult>0</difficult><bndbox><xmin>516</xmin><ymin>232</ymin><xmax>570</xmax><ymax>308</ymax></bndbox></object><object><name>face</name><pose>Unspecified</pose><truncated>0</truncated><difficult>0</difficult><bndbox><xmin>142</xmin><ymin>180</ymin><xmax>196</xmax><ymax>258</ymax></bndbox></object><object><name>face</name><pose>Unspecified</pose><truncated>0</truncated><difficult>0</difficult><bndbox><xmin>290</xmin><ymin>230</ymin><xmax>350</xmax><ymax>310</ymax></bndbox></object><object><name>face</name><pose>Unspecified</pose><truncated>0</truncated><difficult>0</difficult><bndbox><xmin>430</xmin><ymin>154</ymin><xmax>490</xmax><ymax>240</ymax></bndbox></object><object><name>face</name><pose>Unspecified</pose><truncated>0</truncated><difficult>0</difficult><bndbox><xmin>206</xmin><ymin>302</ymin><xmax>284</xmax><ymax>400</ymax></bndbox></object></annotation>