<annotation><folder>12--Group</folder><filename>12_Group_Group_12_Group_Group_12_876.jpg</filename><path>./WIDER_train/images/12--Group/12_Group_Group_12_Group_Group_12_876.jpg</path><source><database>Unknown</database></source><size><width>1024</width><height>765</height><depth>3</depth></size><segmented>0</segmented><object><name>face</name><pose>Unspecified</pose><truncated>0</truncated><difficult>0</difficult><bndbox><xmin>0</xmin><ymin>372</ymin><xmax>34</xmax><ymax>434</ymax></bndbox></object><object><name>face</name><pose>Unspecified</pose><truncated>0</truncated><difficult>0</difficult><bndbox><xmin>106</xmin><ymin>329</ymin><xmax>150</xmax><ymax>393</ymax></bndbox></object><object><name>face</name><pose>Unspecified</pose><truncated>0</truncated><difficult>0</difficult><bndbox><xmin>259</xmin><ymin>279</ymin><xmax>291</xmax><ymax>328</ymax></bndbox></object><object><name>face</name><pose>Unspecified</pose><truncated>0</truncated><difficult>0</difficult><bndbox><xmin>367</xmin><ymin>278</ymin><xmax>396</xmax><ymax>320</ymax></bndbox></object><object><name>face</name><pose>Unspecified</pose><truncated>0</truncated><difficult>0</difficult><bndbox><xmin>419</xmin><ymin>284</ymin><xmax>444</xmax><ymax>320</ymax></bndbox></object><object><name>face</name><pose>Unspecified</pose><truncated>0</truncated><difficult>0</difficult><bndbox><xmin>461</xmin><ymin>270</ymin><xmax>487</xmax><ymax>307</ymax></bndbox></object><object><name>face</name><pose>Unspecified</pose><truncated>0</truncated><difficult>0</difficult><bndbox><xmin>574</xmin><ymin>261</ymin><xmax>600</xmax><ymax>292</ymax></bndbox></object><object><name>face</name><pose>Unspecified</pose><truncated>0</truncated><difficult>0</difficult><bndbox><xmin>696</xmin><ymin>263</ymin><xmax>719</xmax><ymax>293</ymax></bndbox></object><object><name>face</name><pose>Unspecified</pose><truncated>0</truncated><difficult>0</difficult><bndbox><xmin>818</xmin><ymin>276</ymin><xmax>843</xmax><ymax>303</ymax></bndbox></object><object><name>face</name><pose>Unspecified</pose><truncated>0</truncated><difficult>0</difficult><bndbox><xmin>217</xmin><ymin>480</ymin><xmax>268</xmax><ymax>575</ymax></bndbox></object><object><name>face</name><pose>Unspecified</pose><truncated>0</truncated><difficult>0</difficult><bndbox><xmin>921</xmin><ymin>266</ymin><xmax>954</xmax><ymax>313</ymax></bndbox></object></annotation>