<annotation><folder>17--Ceremony</folder><filename>17_Ceremony_Ceremony_17_302.jpg</filename><path>./WIDER_train/images/17--Ceremony/17_Ceremony_Ceremony_17_302.jpg</path><source><database>Unknown</database></source><size><width>1024</width><height>681</height><depth>3</depth></size><segmented>0</segmented><object><name>face</name><pose>Unspecified</pose><truncated>0</truncated><difficult>0</difficult><bndbox><xmin>725</xmin><ymin>349</ymin><xmax>752</xmax><ymax>380</ymax></bndbox></object><object><name>face</name><pose>Unspecified</pose><truncated>0</truncated><difficult>0</difficult><bndbox><xmin>759</xmin><ymin>324</ymin><xmax>782</xmax><ymax>354</ymax></bndbox></object><object><name>face</name><pose>Unspecified</pose><truncated>0</truncated><difficult>0</difficult><bndbox><xmin>538</xmin><ymin>323</ymin><xmax>555</xmax><ymax>354</ymax></bndbox></object><object><name>face</name><pose>Unspecified</pose><truncated>0</truncated><difficult>0</difficult><bndbox><xmin>513</xmin><ymin>327</ymin><xmax>530</xmax><ymax>349</ymax></bndbox></object><object><name>face</name><pose>Unspecified</pose><truncated>0</truncated><difficult>0</difficult><bndbox><xmin>461</xmin><ymin>341</ymin><xmax>478</xmax><ymax>366</ymax></bndbox></object><object><name>face</name><pose>Unspecified</pose><truncated>0</truncated><difficult>0</difficult><bndbox><xmin>410</xmin><ymin>319</ymin><xmax>431</xmax><ymax>353</ymax></bndbox></object><object><name>face</name><pose>Unspecified</pose><truncated>0</truncated><difficult>0</difficult><bndbox><xmin>274</xmin><ymin>325</ymin><xmax>298</xmax><ymax>356</ymax></bndbox></object><object><name>face</name><pose>Unspecified</pose><truncated>0</truncated><difficult>0</difficult><bndbox><xmin>70</xmin><ymin>332</ymin><xmax>98</xmax><ymax>366</ymax></bndbox></object><object><name>face</name><pose>Unspecified</pose><truncated>0</truncated><difficult>0</difficult><bndbox><xmin>251</xmin><ymin>326</ymin><xmax>271</xmax><ymax>352</ymax></bndbox></object><object><name>face</name><pose>Unspecified</pose><truncated>0</truncated><difficult>0</difficult><bndbox><xmin>394</xmin><ymin>318</ymin><xmax>408</xmax><ymax>338</ymax></bndbox></object><object><name>face</name><pose>Unspecified</pose><truncated>0</truncated><difficult>0</difficult><bndbox><xmin>331</xmin><ymin>355</ymin><xmax>335</xmax><ymax>360</ymax></bndbox></object></annotation>