<annotation><folder>20--Family_Group</folder><filename>20_Family_Group_Family_Group_20_918.jpg</filename><path>./WIDER_train/images/20--Family_Group/20_Family_Group_Family_Group_20_918.jpg</path><source><database>Unknown</database></source><size><width>1024</width><height>615</height><depth>3</depth></size><segmented>0</segmented><object><name>face</name><pose>Unspecified</pose><truncated>0</truncated><difficult>0</difficult><bndbox><xmin>85</xmin><ymin>218</ymin><xmax>142</xmax><ymax>287</ymax></bndbox></object><object><name>face</name><pose>Unspecified</pose><truncated>0</truncated><difficult>0</difficult><bndbox><xmin>195</xmin><ymin>34</ymin><xmax>248</xmax><ymax>94</ymax></bndbox></object><object><name>face</name><pose>Unspecified</pose><truncated>0</truncated><difficult>0</difficult><bndbox><xmin>294</xmin><ymin>57</ymin><xmax>341</xmax><ymax>110</ymax></bndbox></object><object><name>face</name><pose>Unspecified</pose><truncated>0</truncated><difficult>0</difficult><bndbox><xmin>352</xmin><ymin>80</ymin><xmax>396</xmax><ymax>138</ymax></bndbox></object><object><name>face</name><pose>Unspecified</pose><truncated>0</truncated><difficult>0</difficult><bndbox><xmin>432</xmin><ymin>63</ymin><xmax>467</xmax><ymax>110</ymax></bndbox></object><object><name>face</name><pose>Unspecified</pose><truncated>0</truncated><difficult>0</difficult><bndbox><xmin>501</xmin><ymin>45</ymin><xmax>547</xmax><ymax>96</ymax></bndbox></object><object><name>face</name><pose>Unspecified</pose><truncated>0</truncated><difficult>0</difficult><bndbox><xmin>346</xmin><ymin>295</ymin><xmax>409</xmax><ymax>365</ymax></bndbox></object><object><name>face</name><pose>Unspecified</pose><truncated>0</truncated><difficult>0</difficult><bndbox><xmin>642</xmin><ymin>60</ymin><xmax>687</xmax><ymax>109</ymax></bndbox></object><object><name>face</name><pose>Unspecified</pose><truncated>0</truncated><difficult>0</difficult><bndbox><xmin>765</xmin><ymin>65</ymin><xmax>809</xmax><ymax>120</ymax></bndbox></object><object><name>face</name><pose>Unspecified</pose><truncated>0</truncated><difficult>0</difficult><bndbox><xmin>867</xmin><ymin>116</ymin><xmax>910</xmax><ymax>169</ymax></bndbox></object><object><name>face</name><pose>Unspecified</pose><truncated>0</truncated><difficult>0</difficult><bndbox><xmin>912</xmin><ymin>124</ymin><xmax>952</xmax><ymax>176</ymax></bndbox></object><object><name>face</name><pose>Unspecified</pose><truncated>0</truncated><difficult>0</difficult><bndbox><xmin>718</xmin><ymin>302</ymin><xmax>770</xmax><ymax>354</ymax></bndbox></object><object><name>face</name><pose>Unspecified</pose><truncated>0</truncated><difficult>0</difficult><bndbox><xmin>569</xmin><ymin>341</ymin><xmax>620</xmax><ymax>403</ymax></bndbox></object><object><name>face</name><pose>Unspecified</pose><truncated>0</truncated><difficult>0</difficult><bndbox><xmin>771</xmin><ymin>265</ymin><xmax>825</xmax><ymax>320</ymax></bndbox></object></annotation>