<annotation><folder>23--Shoppers</folder><filename>23_Shoppers_Shoppers_23_628.jpg</filename><path>./WIDER_train/images/23--Shoppers/23_Shoppers_Shoppers_23_628.jpg</path><source><database>Unknown</database></source><size><width>1024</width><height>1542</height><depth>3</depth></size><segmented>0</segmented><object><name>face</name><pose>Unspecified</pose><truncated>0</truncated><difficult>0</difficult><bndbox><xmin>407</xmin><ymin>114</ymin><xmax>564</xmax><ymax>349</ymax></bndbox></object></annotation>