<annotation><folder>23--Shoppers</folder><filename>23_Shoppers_Shoppers_23_30.jpg</filename><path>./WIDER_train/images/23--Shoppers/23_Shoppers_Shoppers_23_30.jpg</path><source><database>Unknown</database></source><size><width>1024</width><height>685</height><depth>3</depth></size><segmented>0</segmented><object><name>face</name><pose>Unspecified</pose><truncated>0</truncated><difficult>0</difficult><bndbox><xmin>619</xmin><ymin>224</ymin><xmax>633</xmax><ymax>242</ymax></bndbox></object><object><name>face</name><pose>Unspecified</pose><truncated>0</truncated><difficult>0</difficult><bndbox><xmin>598</xmin><ymin>229</ymin><xmax>611</xmax><ymax>246</ymax></bndbox></object><object><name>face</name><pose>Unspecified</pose><truncated>0</truncated><difficult>0</difficult><bndbox><xmin>483</xmin><ymin>238</ymin><xmax>493</xmax><ymax>250</ymax></bndbox></object><object><name>face</name><pose>Unspecified</pose><truncated>0</truncated><difficult>0</difficult><bndbox><xmin>506</xmin><ymin>226</ymin><xmax>518</xmax><ymax>242</ymax></bndbox></object></annotation>