<annotation><folder>26--Soldier_Drilling</folder><filename>26_Soldier_Drilling_Soldiers_Drilling_26_454.jpg</filename><path>./WIDER_train/images/26--Soldier_Drilling/26_Soldier_Drilling_Soldiers_Drilling_26_454.jpg</path><source><database>Unknown</database></source><size><width>1024</width><height>647</height><depth>3</depth></size><segmented>0</segmented><object><name>face</name><pose>Unspecified</pose><truncated>0</truncated><difficult>0</difficult><bndbox><xmin>545</xmin><ymin>380</ymin><xmax>588</xmax><ymax>433</ymax></bndbox></object><object><name>face</name><pose>Unspecified</pose><truncated>0</truncated><difficult>0</difficult><bndbox><xmin>655</xmin><ymin>355</ymin><xmax>705</xmax><ymax>431</ymax></bndbox></object><object><name>face</name><pose>Unspecified</pose><truncated>0</truncated><difficult>0</difficult><bndbox><xmin>125</xmin><ymin>50</ymin><xmax>267</xmax><ymax>271</ymax></bndbox></object><object><name>face</name><pose>Unspecified</pose><truncated>0</truncated><difficult>0</difficult><bndbox><xmin>250</xmin><ymin>249</ymin><xmax>297</xmax><ymax>311</ymax></bndbox></object><object><name>face</name><pose>Unspecified</pose><truncated>0</truncated><difficult>0</difficult><bndbox><xmin>740</xmin><ymin>369</ymin><xmax>784</xmax><ymax>430</ymax></bndbox></object><object><name>face</name><pose>Unspecified</pose><truncated>0</truncated><difficult>0</difficult><bndbox><xmin>786</xmin><ymin>405</ymin><xmax>828</xmax><ymax>466</ymax></bndbox></object><object><name>face</name><pose>Unspecified</pose><truncated>0</truncated><difficult>0</difficult><bndbox><xmin>821</xmin><ymin>374</ymin><xmax>881</xmax><ymax>450</ymax></bndbox></object><object><name>face</name><pose>Unspecified</pose><truncated>0</truncated><difficult>0</difficult><bndbox><xmin>916</xmin><ymin>358</ymin><xmax>950</xmax><ymax>407</ymax></bndbox></object><object><name>face</name><pose>Unspecified</pose><truncated>0</truncated><difficult>0</difficult><bndbox><xmin>968</xmin><ymin>340</ymin><xmax>1022</xmax><ymax>417</ymax></bndbox></object></annotation>