<annotation><folder>2--Demonstration</folder><filename>2_Demonstration_Demonstration_Or_Protest_2_909.jpg</filename><path>./WIDER_train/images/2--Demonstration/2_Demonstration_Demonstration_Or_Protest_2_909.jpg</path><source><database>Unknown</database></source><size><width>1024</width><height>1533</height><depth>3</depth></size><segmented>0</segmented><object><name>face</name><pose>Unspecified</pose><truncated>0</truncated><difficult>0</difficult><bndbox><xmin>74</xmin><ymin>535</ymin><xmax>129</xmax><ymax>607</ymax></bndbox></object><object><name>face</name><pose>Unspecified</pose><truncated>0</truncated><difficult>0</difficult><bndbox><xmin>187</xmin><ymin>580</ymin><xmax>246</xmax><ymax>667</ymax></bndbox></object><object><name>face</name><pose>Unspecified</pose><truncated>0</truncated><difficult>0</difficult><bndbox><xmin>230</xmin><ymin>517</ymin><xmax>313</xmax><ymax>633</ymax></bndbox></object><object><name>face</name><pose>Unspecified</pose><truncated>0</truncated><difficult>0</difficult><bndbox><xmin>432</xmin><ymin>605</ymin><xmax>533</xmax><ymax>733</ymax></bndbox></object><object><name>face</name><pose>Unspecified</pose><truncated>0</truncated><difficult>0</difficult><bndbox><xmin>743</xmin><ymin>425</ymin><xmax>894</xmax><ymax>616</ymax></bndbox></object><object><name>face</name><pose>Unspecified</pose><truncated>0</truncated><difficult>0</difficult><bndbox><xmin>222</xmin><ymin>889</ymin><xmax>246</xmax><ymax>919</ymax></bndbox></object></annotation>