<annotation><folder>34--Baseball</folder><filename>34_Baseball_Baseball_34_655.jpg</filename><path>./WIDER_train/images/34--Baseball/34_Baseball_Baseball_34_655.jpg</path><source><database>Unknown</database></source><size><width>1024</width><height>768</height><depth>3</depth></size><segmented>0</segmented><object><name>face</name><pose>Unspecified</pose><truncated>0</truncated><difficult>0</difficult><bndbox><xmin>123</xmin><ymin>122</ymin><xmax>155</xmax><ymax>162</ymax></bndbox></object><object><name>face</name><pose>Unspecified</pose><truncated>0</truncated><difficult>0</difficult><bndbox><xmin>159</xmin><ymin>74</ymin><xmax>189</xmax><ymax>114</ymax></bndbox></object><object><name>face</name><pose>Unspecified</pose><truncated>0</truncated><difficult>0</difficult><bndbox><xmin>230</xmin><ymin>100</ymin><xmax>263</xmax><ymax>144</ymax></bndbox></object><object><name>face</name><pose>Unspecified</pose><truncated>0</truncated><difficult>0</difficult><bndbox><xmin>331</xmin><ymin>116</ymin><xmax>360</xmax><ymax>159</ymax></bndbox></object><object><name>face</name><pose>Unspecified</pose><truncated>0</truncated><difficult>0</difficult><bndbox><xmin>116</xmin><ymin>64</ymin><xmax>142</xmax><ymax>98</ymax></bndbox></object><object><name>face</name><pose>Unspecified</pose><truncated>0</truncated><difficult>0</difficult><bndbox><xmin>89</xmin><ymin>10</ymin><xmax>119</xmax><ymax>52</ymax></bndbox></object><object><name>face</name><pose>Unspecified</pose><truncated>0</truncated><difficult>0</difficult><bndbox><xmin>124</xmin><ymin>265</ymin><xmax>153</xmax><ymax>305</ymax></bndbox></object><object><name>face</name><pose>Unspecified</pose><truncated>0</truncated><difficult>0</difficult><bndbox><xmin>215</xmin><ymin>604</ymin><xmax>250</xmax><ymax>642</ymax></bndbox></object><object><name>face</name><pose>Unspecified</pose><truncated>0</truncated><difficult>0</difficult><bndbox><xmin>295</xmin><ymin>572</ymin><xmax>330</xmax><ymax>620</ymax></bndbox></object><object><name>face</name><pose>Unspecified</pose><truncated>0</truncated><difficult>0</difficult><bndbox><xmin>173</xmin><ymin>494</ymin><xmax>204</xmax><ymax>544</ymax></bndbox></object><object><name>face</name><pose>Unspecified</pose><truncated>0</truncated><difficult>0</difficult><bndbox><xmin>54</xmin><ymin>500</ymin><xmax>84</xmax><ymax>544</ymax></bndbox></object><object><name>face</name><pose>Unspecified</pose><truncated>0</truncated><difficult>0</difficult><bndbox><xmin>96</xmin><ymin>310</ymin><xmax>127</xmax><ymax>361</ymax></bndbox></object><object><name>face</name><pose>Unspecified</pose><truncated>0</truncated><difficult>0</difficult><bndbox><xmin>220</xmin><ymin>363</ymin><xmax>253</xmax><ymax>408</ymax></bndbox></object><object><name>face</name><pose>Unspecified</pose><truncated>0</truncated><difficult>0</difficult><bndbox><xmin>275</xmin><ymin>318</ymin><xmax>308</xmax><ymax>356</ymax></bndbox></object><object><name>face</name><pose>Unspecified</pose><truncated>0</truncated><difficult>0</difficult><bndbox><xmin>180</xmin><ymin>321</ymin><xmax>211</xmax><ymax>364</ymax></bndbox></object><object><name>face</name><pose>Unspecified</pose><truncated>0</truncated><difficult>0</difficult><bndbox><xmin>166</xmin><ymin>588</ymin><xmax>193</xmax><ymax>631</ymax></bndbox></object><object><name>face</name><pose>Unspecified</pose><truncated>0</truncated><difficult>0</difficult><bndbox><xmin>307</xmin><ymin>280</ymin><xmax>337</xmax><ymax>320</ymax></bndbox></object><object><name>face</name><pose>Unspecified</pose><truncated>0</truncated><difficult>0</difficult><bndbox><xmin>727</xmin><ymin>261</ymin><xmax>759</xmax><ymax>307</ymax></bndbox></object><object><name>face</name><pose>Unspecified</pose><truncated>0</truncated><difficult>0</difficult><bndbox><xmin>934</xmin><ymin>269</ymin><xmax>966</xmax><ymax>305</ymax></bndbox></object><object><name>face</name><pose>Unspecified</pose><truncated>0</truncated><difficult>0</difficult><bndbox><xmin>830</xmin><ymin>204</ymin><xmax>864</xmax><ymax>240</ymax></bndbox></object><object><name>face</name><pose>Unspecified</pose><truncated>0</truncated><difficult>0</difficult><bndbox><xmin>789</xmin><ymin>210</ymin><xmax>821</xmax><ymax>247</ymax></bndbox></object><object><name>face</name><pose>Unspecified</pose><truncated>0</truncated><difficult>0</difficult><bndbox><xmin>759</xmin><ymin>185</ymin><xmax>789</xmax><ymax>217</ymax></bndbox></object><object><name>face</name><pose>Unspecified</pose><truncated>0</truncated><difficult>0</difficult><bndbox><xmin>785</xmin><ymin>145</ymin><xmax>821</xmax><ymax>184</ymax></bndbox></object><object><name>face</name><pose>Unspecified</pose><truncated>0</truncated><difficult>0</difficult><bndbox><xmin>691</xmin><ymin>229</ymin><xmax>721</xmax><ymax>267</ymax></bndbox></object><object><name>face</name><pose>Unspecified</pose><truncated>0</truncated><difficult>0</difficult><bndbox><xmin>816</xmin><ymin>28</ymin><xmax>848</xmax><ymax>68</ymax></bndbox></object><object><name>face</name><pose>Unspecified</pose><truncated>0</truncated><difficult>0</difficult><bndbox><xmin>950</xmin><ymin>67</ymin><xmax>983</xmax><ymax>111</ymax></bndbox></object><object><name>face</name><pose>Unspecified</pose><truncated>0</truncated><difficult>0</difficult><bndbox><xmin>850</xmin><ymin>277</ymin><xmax>879</xmax><ymax>316</ymax></bndbox></object><object><name>face</name><pose>Unspecified</pose><truncated>0</truncated><difficult>0</difficult><bndbox><xmin>724</xmin><ymin>43</ymin><xmax>752</xmax><ymax>79</ymax></bndbox></object><object><name>face</name><pose>Unspecified</pose><truncated>0</truncated><difficult>0</difficult><bndbox><xmin>625</xmin><ymin>43</ymin><xmax>656</xmax><ymax>81</ymax></bndbox></object><object><name>face</name><pose>Unspecified</pose><truncated>0</truncated><difficult>0</difficult><bndbox><xmin>979</xmin><ymin>179</ymin><xmax>1009</xmax><ymax>212</ymax></bndbox></object><object><name>face</name><pose>Unspecified</pose><truncated>0</truncated><difficult>0</difficult><bndbox><xmin>765</xmin><ymin>310</ymin><xmax>799</xmax><ymax>350</ymax></bndbox></object><object><name>face</name><pose>Unspecified</pose><truncated>0</truncated><difficult>0</difficult><bndbox><xmin>872</xmin><ymin>463</ymin><xmax>910</xmax><ymax>511</ymax></bndbox></object><object><name>face</name><pose>Unspecified</pose><truncated>0</truncated><difficult>0</difficult><bndbox><xmin>946</xmin><ymin>378</ymin><xmax>979</xmax><ymax>418</ymax></bndbox></object><object><name>face</name><pose>Unspecified</pose><truncated>0</truncated><difficult>0</difficult><bndbox><xmin>759</xmin><ymin>376</ymin><xmax>794</xmax><ymax>422</ymax></bndbox></object><object><name>face</name><pose>Unspecified</pose><truncated>0</truncated><difficult>0</difficult><bndbox><xmin>754</xmin><ymin>500</ymin><xmax>793</xmax><ymax>545</ymax></bndbox></object><object><name>face</name><pose>Unspecified</pose><truncated>0</truncated><difficult>0</difficult><bndbox><xmin>779</xmin><ymin>608</ymin><xmax>818</xmax><ymax>659</ymax></bndbox></object></annotation>