<annotation><folder>37--Soccer</folder><filename>37_Soccer_soccer_ball_37_608.jpg</filename><path>./WIDER_train/images/37--Soccer/37_Soccer_soccer_ball_37_608.jpg</path><source><database>Unknown</database></source><size><width>1024</width><height>768</height><depth>3</depth></size><segmented>0</segmented><object><name>face</name><pose>Unspecified</pose><truncated>0</truncated><difficult>0</difficult><bndbox><xmin>54</xmin><ymin>312</ymin><xmax>78</xmax><ymax>352</ymax></bndbox></object><object><name>face</name><pose>Unspecified</pose><truncated>0</truncated><difficult>0</difficult><bndbox><xmin>117</xmin><ymin>318</ymin><xmax>131</xmax><ymax>334</ymax></bndbox></object><object><name>face</name><pose>Unspecified</pose><truncated>0</truncated><difficult>0</difficult><bndbox><xmin>335</xmin><ymin>363</ymin><xmax>363</xmax><ymax>397</ymax></bndbox></object><object><name>face</name><pose>Unspecified</pose><truncated>0</truncated><difficult>0</difficult><bndbox><xmin>272</xmin><ymin>326</ymin><xmax>291</xmax><ymax>358</ymax></bndbox></object><object><name>face</name><pose>Unspecified</pose><truncated>0</truncated><difficult>0</difficult><bndbox><xmin>309</xmin><ymin>313</ymin><xmax>326</xmax><ymax>343</ymax></bndbox></object><object><name>face</name><pose>Unspecified</pose><truncated>0</truncated><difficult>0</difficult><bndbox><xmin>250</xmin><ymin>319</ymin><xmax>266</xmax><ymax>350</ymax></bndbox></object><object><name>face</name><pose>Unspecified</pose><truncated>0</truncated><difficult>0</difficult><bndbox><xmin>223</xmin><ymin>302</ymin><xmax>244</xmax><ymax>336</ymax></bndbox></object><object><name>face</name><pose>Unspecified</pose><truncated>0</truncated><difficult>0</difficult><bndbox><xmin>339</xmin><ymin>299</ymin><xmax>354</xmax><ymax>324</ymax></bndbox></object><object><name>face</name><pose>Unspecified</pose><truncated>0</truncated><difficult>0</difficult><bndbox><xmin>474</xmin><ymin>286</ymin><xmax>502</xmax><ymax>328</ymax></bndbox></object><object><name>face</name><pose>Unspecified</pose><truncated>0</truncated><difficult>0</difficult><bndbox><xmin>543</xmin><ymin>305</ymin><xmax>571</xmax><ymax>344</ymax></bndbox></object><object><name>face</name><pose>Unspecified</pose><truncated>0</truncated><difficult>0</difficult><bndbox><xmin>580</xmin><ymin>304</ymin><xmax>595</xmax><ymax>328</ymax></bndbox></object><object><name>face</name><pose>Unspecified</pose><truncated>0</truncated><difficult>0</difficult><bndbox><xmin>611</xmin><ymin>327</ymin><xmax>635</xmax><ymax>363</ymax></bndbox></object><object><name>face</name><pose>Unspecified</pose><truncated>0</truncated><difficult>0</difficult><bndbox><xmin>629</xmin><ymin>287</ymin><xmax>648</xmax><ymax>312</ymax></bndbox></object><object><name>face</name><pose>Unspecified</pose><truncated>0</truncated><difficult>0</difficult><bndbox><xmin>661</xmin><ymin>307</ymin><xmax>686</xmax><ymax>345</ymax></bndbox></object><object><name>face</name><pose>Unspecified</pose><truncated>0</truncated><difficult>0</difficult><bndbox><xmin>691</xmin><ymin>319</ymin><xmax>717</xmax><ymax>362</ymax></bndbox></object><object><name>face</name><pose>Unspecified</pose><truncated>0</truncated><difficult>0</difficult><bndbox><xmin>742</xmin><ymin>309</ymin><xmax>773</xmax><ymax>346</ymax></bndbox></object><object><name>face</name><pose>Unspecified</pose><truncated>0</truncated><difficult>0</difficult><bndbox><xmin>724</xmin><ymin>341</ymin><xmax>745</xmax><ymax>363</ymax></bndbox></object><object><name>face</name><pose>Unspecified</pose><truncated>0</truncated><difficult>0</difficult><bndbox><xmin>809</xmin><ymin>377</ymin><xmax>837</xmax><ymax>418</ymax></bndbox></object><object><name>face</name><pose>Unspecified</pose><truncated>0</truncated><difficult>0</difficult><bndbox><xmin>788</xmin><ymin>464</ymin><xmax>823</xmax><ymax>508</ymax></bndbox></object><object><name>face</name><pose>Unspecified</pose><truncated>0</truncated><difficult>0</difficult><bndbox><xmin>888</xmin><ymin>337</ymin><xmax>907</xmax><ymax>367</ymax></bndbox></object><object><name>face</name><pose>Unspecified</pose><truncated>0</truncated><difficult>0</difficult><bndbox><xmin>972</xmin><ymin>334</ymin><xmax>988</xmax><ymax>364</ymax></bndbox></object><object><name>face</name><pose>Unspecified</pose><truncated>0</truncated><difficult>0</difficult><bndbox><xmin>232</xmin><ymin>474</ymin><xmax>267</xmax><ymax>510</ymax></bndbox></object><object><name>face</name><pose>Unspecified</pose><truncated>0</truncated><difficult>0</difficult><bndbox><xmin>298</xmin><ymin>293</ymin><xmax>312</xmax><ymax>311</ymax></bndbox></object><object><name>face</name><pose>Unspecified</pose><truncated>0</truncated><difficult>0</difficult><bndbox><xmin>267</xmin><ymin>292</ymin><xmax>283</xmax><ymax>310</ymax></bndbox></object><object><name>face</name><pose>Unspecified</pose><truncated>0</truncated><difficult>0</difficult><bndbox><xmin>173</xmin><ymin>295</ymin><xmax>187</xmax><ymax>312</ymax></bndbox></object><object><name>face</name><pose>Unspecified</pose><truncated>0</truncated><difficult>0</difficult><bndbox><xmin>97</xmin><ymin>344</ymin><xmax>112</xmax><ymax>363</ymax></bndbox></object><object><name>face</name><pose>Unspecified</pose><truncated>0</truncated><difficult>0</difficult><bndbox><xmin>325</xmin><ymin>281</ymin><xmax>339</xmax><ymax>298</ymax></bndbox></object><object><name>face</name><pose>Unspecified</pose><truncated>0</truncated><difficult>0</difficult><bndbox><xmin>377</xmin><ymin>277</ymin><xmax>386</xmax><ymax>292</ymax></bndbox></object><object><name>face</name><pose>Unspecified</pose><truncated>0</truncated><difficult>0</difficult><bndbox><xmin>388</xmin><ymin>309</ymin><xmax>404</xmax><ymax>332</ymax></bndbox></object><object><name>face</name><pose>Unspecified</pose><truncated>0</truncated><difficult>0</difficult><bndbox><xmin>817</xmin><ymin>343</ymin><xmax>838</xmax><ymax>368</ymax></bndbox></object></annotation>