<annotation><folder>3--Riot</folder><filename>3_Riot_Riot_3_584.jpg</filename><path>./WIDER_train/images/3--Riot/3_Riot_Riot_3_584.jpg</path><source><database>Unknown</database></source><size><width>1024</width><height>687</height><depth>3</depth></size><segmented>0</segmented><object><name>face</name><pose>Unspecified</pose><truncated>0</truncated><difficult>0</difficult><bndbox><xmin>684</xmin><ymin>90</ymin><xmax>773</xmax><ymax>205</ymax></bndbox></object><object><name>face</name><pose>Unspecified</pose><truncated>0</truncated><difficult>0</difficult><bndbox><xmin>316</xmin><ymin>294</ymin><xmax>344</xmax><ymax>324</ymax></bndbox></object><object><name>face</name><pose>Unspecified</pose><truncated>0</truncated><difficult>0</difficult><bndbox><xmin>1</xmin><ymin>359</ymin><xmax>10</xmax><ymax>373</ymax></bndbox></object></annotation>