<annotation><folder>46--Jockey</folder><filename>46_Jockey_Jockey_46_575.jpg</filename><path>./WIDER_train/images/46--Jockey/46_Jockey_Jockey_46_575.jpg</path><source><database>Unknown</database></source><size><width>1024</width><height>412</height><depth>3</depth></size><segmented>0</segmented><object><name>face</name><pose>Unspecified</pose><truncated>0</truncated><difficult>0</difficult><bndbox><xmin>229</xmin><ymin>12</ymin><xmax>255</xmax><ymax>44</ymax></bndbox></object><object><name>face</name><pose>Unspecified</pose><truncated>0</truncated><difficult>0</difficult><bndbox><xmin>341</xmin><ymin>85</ymin><xmax>372</xmax><ymax>117</ymax></bndbox></object><object><name>face</name><pose>Unspecified</pose><truncated>0</truncated><difficult>0</difficult><bndbox><xmin>422</xmin><ymin>75</ymin><xmax>451</xmax><ymax>108</ymax></bndbox></object><object><name>face</name><pose>Unspecified</pose><truncated>0</truncated><difficult>0</difficult><bndbox><xmin>576</xmin><ymin>133</ymin><xmax>614</xmax><ymax>169</ymax></bndbox></object><object><name>face</name><pose>Unspecified</pose><truncated>0</truncated><difficult>0</difficult><bndbox><xmin>338</xmin><ymin>148</ymin><xmax>370</xmax><ymax>183</ymax></bndbox></object><object><name>face</name><pose>Unspecified</pose><truncated>0</truncated><difficult>0</difficult><bndbox><xmin>196</xmin><ymin>75</ymin><xmax>228</xmax><ymax>106</ymax></bndbox></object></annotation>