<annotation><folder>48--Parachutist_Paratrooper</folder><filename>48_Parachutist_Paratrooper_Parachutist_Paratrooper_48_733.jpg</filename><path>./WIDER_train/images/48--Parachutist_Paratrooper/48_Parachutist_Paratrooper_Parachutist_Paratrooper_48_733.jpg</path><source><database>Unknown</database></source><size><width>1024</width><height>686</height><depth>3</depth></size><segmented>0</segmented><object><name>face</name><pose>Unspecified</pose><truncated>0</truncated><difficult>0</difficult><bndbox><xmin>730</xmin><ymin>134</ymin><xmax>890</xmax><ymax>276</ymax></bndbox></object><object><name>face</name><pose>Unspecified</pose><truncated>0</truncated><difficult>0</difficult><bndbox><xmin>508</xmin><ymin>240</ymin><xmax>608</xmax><ymax>336</ymax></bndbox></object><object><name>face</name><pose>Unspecified</pose><truncated>0</truncated><difficult>0</difficult><bndbox><xmin>362</xmin><ymin>214</ymin><xmax>448</xmax><ymax>318</ymax></bndbox></object><object><name>face</name><pose>Unspecified</pose><truncated>0</truncated><difficult>0</difficult><bndbox><xmin>274</xmin><ymin>206</ymin><xmax>350</xmax><ymax>298</ymax></bndbox></object><object><name>face</name><pose>Unspecified</pose><truncated>0</truncated><difficult>0</difficult><bndbox><xmin>214</xmin><ymin>212</ymin><xmax>276</xmax><ymax>282</ymax></bndbox></object><object><name>face</name><pose>Unspecified</pose><truncated>0</truncated><difficult>0</difficult><bndbox><xmin>124</xmin><ymin>206</ymin><xmax>176</xmax><ymax>270</ymax></bndbox></object></annotation>