<annotation><folder>50--Celebration_Or_Party</folder><filename>50_Celebration_Or_Party_houseparty_50_30.jpg</filename><path>./WIDER_train/images/50--Celebration_Or_Party/50_Celebration_Or_Party_houseparty_50_30.jpg</path><source><database>Unknown</database></source><size><width>1024</width><height>576</height><depth>3</depth></size><segmented>0</segmented><object><name>face</name><pose>Unspecified</pose><truncated>0</truncated><difficult>0</difficult><bndbox><xmin>653</xmin><ymin>289</ymin><xmax>740</xmax><ymax>431</ymax></bndbox></object><object><name>face</name><pose>Unspecified</pose><truncated>0</truncated><difficult>0</difficult><bndbox><xmin>481</xmin><ymin>206</ymin><xmax>562</xmax><ymax>305</ymax></bndbox></object><object><name>face</name><pose>Unspecified</pose><truncated>0</truncated><difficult>0</difficult><bndbox><xmin>385</xmin><ymin>212</ymin><xmax>462</xmax><ymax>311</ymax></bndbox></object><object><name>face</name><pose>Unspecified</pose><truncated>0</truncated><difficult>0</difficult><bndbox><xmin>757</xmin><ymin>75</ymin><xmax>791</xmax><ymax>133</ymax></bndbox></object><object><name>face</name><pose>Unspecified</pose><truncated>0</truncated><difficult>0</difficult><bndbox><xmin>646</xmin><ymin>78</ymin><xmax>694</xmax><ymax>151</ymax></bndbox></object><object><name>face</name><pose>Unspecified</pose><truncated>0</truncated><difficult>0</difficult><bndbox><xmin>592</xmin><ymin>17</ymin><xmax>645</xmax><ymax>89</ymax></bndbox></object><object><name>face</name><pose>Unspecified</pose><truncated>0</truncated><difficult>0</difficult><bndbox><xmin>506</xmin><ymin>43</ymin><xmax>558</xmax><ymax>109</ymax></bndbox></object><object><name>face</name><pose>Unspecified</pose><truncated>0</truncated><difficult>0</difficult><bndbox><xmin>267</xmin><ymin>180</ymin><xmax>321</xmax><ymax>255</ymax></bndbox></object><object><name>face</name><pose>Unspecified</pose><truncated>0</truncated><difficult>0</difficult><bndbox><xmin>192</xmin><ymin>148</ymin><xmax>226</xmax><ymax>193</ymax></bndbox></object><object><name>face</name><pose>Unspecified</pose><truncated>0</truncated><difficult>0</difficult><bndbox><xmin>132</xmin><ymin>172</ymin><xmax>164</xmax><ymax>218</ymax></bndbox></object></annotation>