<annotation><folder>50--Celebration_Or_Party</folder><filename>50_Celebration_Or_Party_houseparty_50_420.jpg</filename><path>./WIDER_train/images/50--Celebration_Or_Party/50_Celebration_Or_Party_houseparty_50_420.jpg</path><source><database>Unknown</database></source><size><width>1024</width><height>1024</height><depth>3</depth></size><segmented>0</segmented><object><name>face</name><pose>Unspecified</pose><truncated>0</truncated><difficult>0</difficult><bndbox><xmin>413</xmin><ymin>456</ymin><xmax>448</xmax><ymax>502</ymax></bndbox></object><object><name>face</name><pose>Unspecified</pose><truncated>0</truncated><difficult>0</difficult><bndbox><xmin>474</xmin><ymin>453</ymin><xmax>506</xmax><ymax>504</ymax></bndbox></object><object><name>face</name><pose>Unspecified</pose><truncated>0</truncated><difficult>0</difficult><bndbox><xmin>565</xmin><ymin>499</ymin><xmax>600</xmax><ymax>556</ymax></bndbox></object><object><name>face</name><pose>Unspecified</pose><truncated>0</truncated><difficult>0</difficult><bndbox><xmin>633</xmin><ymin>370</ymin><xmax>668</xmax><ymax>413</ymax></bndbox></object><object><name>face</name><pose>Unspecified</pose><truncated>0</truncated><difficult>0</difficult><bndbox><xmin>583</xmin><ymin>364</ymin><xmax>613</xmax><ymax>402</ymax></bndbox></object></annotation>