<annotation><folder>53--Raid</folder><filename>53_Raid_policeraid_53_729.jpg</filename><path>./WIDER_train/images/53--Raid/53_Raid_policeraid_53_729.jpg</path><source><database>Unknown</database></source><size><width>1024</width><height>740</height><depth>3</depth></size><segmented>0</segmented><object><name>face</name><pose>Unspecified</pose><truncated>0</truncated><difficult>0</difficult><bndbox><xmin>245</xmin><ymin>410</ymin><xmax>371</xmax><ymax>697</ymax></bndbox></object><object><name>face</name><pose>Unspecified</pose><truncated>0</truncated><difficult>0</difficult><bndbox><xmin>253</xmin><ymin>174</ymin><xmax>276</xmax><ymax>207</ymax></bndbox></object><object><name>face</name><pose>Unspecified</pose><truncated>0</truncated><difficult>0</difficult><bndbox><xmin>497</xmin><ymin>244</ymin><xmax>522</xmax><ymax>266</ymax></bndbox></object><object><name>face</name><pose>Unspecified</pose><truncated>0</truncated><difficult>0</difficult><bndbox><xmin>728</xmin><ymin>197</ymin><xmax>745</xmax><ymax>221</ymax></bndbox></object><object><name>face</name><pose>Unspecified</pose><truncated>0</truncated><difficult>0</difficult><bndbox><xmin>661</xmin><ymin>242</ymin><xmax>683</xmax><ymax>261</ymax></bndbox></object><object><name>face</name><pose>Unspecified</pose><truncated>0</truncated><difficult>0</difficult><bndbox><xmin>772</xmin><ymin>337</ymin><xmax>797</xmax><ymax>357</ymax></bndbox></object><object><name>face</name><pose>Unspecified</pose><truncated>0</truncated><difficult>0</difficult><bndbox><xmin>961</xmin><ymin>181</ymin><xmax>991</xmax><ymax>230</ymax></bndbox></object></annotation>