<annotation><folder>54--Rescue</folder><filename>54_Rescue_firemanrescue_54_834.jpg</filename><path>./WIDER_train/images/54--Rescue/54_Rescue_firemanrescue_54_834.jpg</path><source><database>Unknown</database></source><size><width>1024</width><height>1525</height><depth>3</depth></size><segmented>0</segmented><object><name>face</name><pose>Unspecified</pose><truncated>0</truncated><difficult>0</difficult><bndbox><xmin>705</xmin><ymin>92</ymin><xmax>815</xmax><ymax>271</ymax></bndbox></object></annotation>