<annotation><folder>55--Sports_Coach_Trainer</folder><filename>55_Sports_Coach_Trainer_sportcoaching_55_857.jpg</filename><path>./WIDER_train/images/55--Sports_Coach_Trainer/55_Sports_Coach_Trainer_sportcoaching_55_857.jpg</path><source><database>Unknown</database></source><size><width>1024</width><height>683</height><depth>3</depth></size><segmented>0</segmented><object><name>face</name><pose>Unspecified</pose><truncated>0</truncated><difficult>0</difficult><bndbox><xmin>62</xmin><ymin>170</ymin><xmax>118</xmax><ymax>242</ymax></bndbox></object><object><name>face</name><pose>Unspecified</pose><truncated>0</truncated><difficult>0</difficult><bndbox><xmin>556</xmin><ymin>266</ymin><xmax>618</xmax><ymax>350</ymax></bndbox></object></annotation>