<annotation><folder>56--Voter</folder><filename>56_Voter_peoplevoting_56_424.jpg</filename><path>./WIDER_train/images/56--Voter/56_Voter_peoplevoting_56_424.jpg</path><source><database>Unknown</database></source><size><width>1024</width><height>769</height><depth>3</depth></size><segmented>0</segmented><object><name>face</name><pose>Unspecified</pose><truncated>0</truncated><difficult>0</difficult><bndbox><xmin>476</xmin><ymin>108</ymin><xmax>610</xmax><ymax>302</ymax></bndbox></object><object><name>face</name><pose>Unspecified</pose><truncated>0</truncated><difficult>0</difficult><bndbox><xmin>901</xmin><ymin>126</ymin><xmax>954</xmax><ymax>189</ymax></bndbox></object><object><name>face</name><pose>Unspecified</pose><truncated>0</truncated><difficult>0</difficult><bndbox><xmin>322</xmin><ymin>108</ymin><xmax>368</xmax><ymax>175</ymax></bndbox></object><object><name>face</name><pose>Unspecified</pose><truncated>0</truncated><difficult>0</difficult><bndbox><xmin>177</xmin><ymin>184</ymin><xmax>196</xmax><ymax>211</ymax></bndbox></object><object><name>face</name><pose>Unspecified</pose><truncated>0</truncated><difficult>0</difficult><bndbox><xmin>410</xmin><ymin>200</ymin><xmax>421</xmax><ymax>210</ymax></bndbox></object><object><name>face</name><pose>Unspecified</pose><truncated>0</truncated><difficult>0</difficult><bndbox><xmin>628</xmin><ymin>183</ymin><xmax>643</xmax><ymax>207</ymax></bndbox></object></annotation>